crip/__init__.py
crip/_typing.py
crip/io.py
crip/lowdose.py
crip/mangoct.py
crip/metric.py
crip/physics.py
crip/plot.py
crip/postprocess.py
crip/preprocess.py
crip/shared.py
crip/spec.py
crip/utils.py
crip/_asset/atten/density.json
crip/_asset/atten/data/Adipose.txt
crip/_asset/atten/data/Air.txt
crip/_asset/atten/data/Al.txt
crip/_asset/atten/data/Au.txt
crip/_asset/atten/data/Blood.txt
crip/_asset/atten/data/Bone.txt
crip/_asset/atten/data/Breast.txt
crip/_asset/atten/data/C.txt
crip/_asset/atten/data/Ca.txt
crip/_asset/atten/data/CaCl2.txt
crip/_asset/atten/data/CaF2.txt
crip/_asset/atten/data/CdTe.txt
crip/_asset/atten/data/Cl.txt
crip/_asset/atten/data/Cu.txt
crip/_asset/atten/data/F.txt
crip/_asset/atten/data/Fe.txt
crip/_asset/atten/data/Gd.txt
crip/_asset/atten/data/H.txt
crip/_asset/atten/data/I.txt
crip/_asset/atten/data/Muscle.txt
crip/_asset/atten/data/N.txt
crip/_asset/atten/data/Na.txt
crip/_asset/atten/data/Ni.txt
crip/_asset/atten/data/O.txt
crip/_asset/atten/data/P.txt
crip/_asset/atten/data/PE.txt
crip/_asset/atten/data/PET.txt
crip/_asset/atten/data/PMMA.txt
crip/_asset/atten/data/Pyrex.txt
crip/_asset/atten/data/S.txt
crip/_asset/atten/data/Si.txt
crip/_asset/atten/data/Sn.txt
crip/_asset/atten/data/SoftTissue.txt
crip/_asset/atten/data/Teflon.txt
crip/_asset/atten/data/Water.txt
crip/_asset/atten/data/WhiteMatter.txt
crip/_asset/shepplogan/1024.tif
crip/_asset/shepplogan/256.tif
crip/_asset/shepplogan/512.tif
crip-1.8.5.dist-info/LICENSE
crip-1.8.5.dist-info/METADATA
crip-1.8.5.dist-info/WHEEL
crip-1.8.5.dist-info/top_level.txt
crip-1.8.5.dist-info/RECORD
