Metadata-Version: 2.1
Name: crip
Version: 1.8.5
Summary: CT Recon in Python is an All-in-one toolkit for CT Data IO, Pre/Post-process, Physics, Dual Energy, Low Dose and everything.
Home-page: https://github.com/SEU-CT-Recon
Author: SEU-CT-Recon
Author-email: zx.cs@qq.com
License: MIT License
License-File: LICENSE
Requires-Dist: numpy
Requires-Dist: opencv-python
Requires-Dist: tifffile
Requires-Dist: pydicom
Requires-Dist: natsort
Requires-Dist: matplotlib
Requires-Dist: scikit-image
Requires-Dist: periodictable
